destined/__init__.py
destined/cli.py
destined/distribution.py
destined/generators.py
destined-0.1.0.dist-info/METADATA
destined-0.1.0.dist-info/RECORD
destined-0.1.0.dist-info/WHEEL
destined-0.1.0.dist-info/entry_points.txt
destined-0.1.0.dist-info/top_level.txt
