Metadata-Version: 2.1
Name: destined
Version: 0.1.0
Summary: Declarative specification for test instance distributions.
Home-page: https://github.com/simonbowly/destined
Author: Simon Bowly
Author-email: simon.bowly@gmail.com
License: MIT license
Keywords: destined
Platform: UNKNOWN
Classifier: Development Status :: 2 - Pre-Alpha
Classifier: Intended Audience :: Developers
Classifier: License :: OSI Approved :: MIT License
Classifier: Natural Language :: English
Classifier: Programming Language :: Python :: 2
Classifier: Programming Language :: Python :: 2.7
Classifier: Programming Language :: Python :: 3
Classifier: Programming Language :: Python :: 3.5
Classifier: Programming Language :: Python :: 3.6
Requires-Dist: click (>=6.0)
Requires-Dist: networkx (>=2.1)
Requires-Dist: tqdm (>=4.19.7)
Requires-Dist: msgpack (>=0.5.6)
Requires-Dist: pyzmq (>=17.0)
